huaweicloudsdkidentitycenterscim/__init__.py
huaweicloudsdkidentitycenterscim/v1/__init__.py
huaweicloudsdkidentitycenterscim/v1/identitycenterscim_async_client.py
huaweicloudsdkidentitycenterscim/v1/identitycenterscim_client.py
huaweicloudsdkidentitycenterscim/v1/identitycenterscim_credentials.py
huaweicloudsdkidentitycenterscim/v1/model/__init__.py
huaweicloudsdkidentitycenterscim/v1/model/address_item_dto.py
huaweicloudsdkidentitycenterscim/v1/model/authentication_scheme_item_dto.py
huaweicloudsdkidentitycenterscim/v1/model/bulk_dto.py
huaweicloudsdkidentitycenterscim/v1/model/change_password_dto.py
huaweicloudsdkidentitycenterscim/v1/model/create_group_req_body.py
huaweicloudsdkidentitycenterscim/v1/model/create_group_request.py
huaweicloudsdkidentitycenterscim/v1/model/create_group_response.py
huaweicloudsdkidentitycenterscim/v1/model/create_user_req_body.py
huaweicloudsdkidentitycenterscim/v1/model/create_user_request.py
huaweicloudsdkidentitycenterscim/v1/model/create_user_response.py
huaweicloudsdkidentitycenterscim/v1/model/delete_group_request.py
huaweicloudsdkidentitycenterscim/v1/model/delete_group_response.py
huaweicloudsdkidentitycenterscim/v1/model/delete_user_request.py
huaweicloudsdkidentitycenterscim/v1/model/delete_user_response.py
huaweicloudsdkidentitycenterscim/v1/model/email_item_dto.py
huaweicloudsdkidentitycenterscim/v1/model/enterprise_dto.py
huaweicloudsdkidentitycenterscim/v1/model/etag_dto.py
huaweicloudsdkidentitycenterscim/v1/model/filter_dto.py
huaweicloudsdkidentitycenterscim/v1/model/get_group_request.py
huaweicloudsdkidentitycenterscim/v1/model/get_group_resp.py
huaweicloudsdkidentitycenterscim/v1/model/get_group_response.py
huaweicloudsdkidentitycenterscim/v1/model/get_user_request.py
huaweicloudsdkidentitycenterscim/v1/model/get_user_resp.py
huaweicloudsdkidentitycenterscim/v1/model/get_user_response.py
huaweicloudsdkidentitycenterscim/v1/model/list_groups_request.py
huaweicloudsdkidentitycenterscim-3.1.184.dist-info/METADATA
huaweicloudsdkidentitycenterscim-3.1.184.dist-info/WHEEL
huaweicloudsdkidentitycenterscim-3.1.184.dist-info/licenses/LICENSE
huaweicloudsdkidentitycenterscim-3.1.184.dist-info/RECORD
